twenty48/Board.py
twenty48/Display.py
twenty48/Game.py
twenty48/GameInformation.py
twenty48/Input.py
twenty48/__init__.py
twenty48-0.0.2.dist-info/METADATA
twenty48-0.0.2.dist-info/WHEEL
twenty48-0.0.2.dist-info/licenses/LICENSE
twenty48-0.0.2.dist-info/RECORD
