Metadata-Version: 2.1
Name: twenty48
Version: 0.0.2
Summary: 2048 game designed for use with AI players.
Project-URL: Homepage, https://github.com/KyleJMcMaster/twenty48
Project-URL: Bug Tracker, https://github.com/KyleJMcMaster/twenty48/issues
Author-email: Kyle McMaster <kyle.mcmaster02@gmail.com>
License-File: LICENSE
Classifier: License :: OSI Approved :: MIT License
Classifier: Operating System :: OS Independent
Classifier: Programming Language :: Python :: 3
Requires-Python: >=3.8
